PyNlpProcessor/PyNlpProcessor.py
PyNlpProcessor/__init__.py
PyNlProcessor-0.2.dist-info/METADATA
PyNlProcessor-0.2.dist-info/WHEEL
PyNlProcessor-0.2.dist-info/top_level.txt
PyNlProcessor-0.2.dist-info/RECORD
